LICENSE
MANIFEST.in
README.rst
requirements.txt
setup.cfg
setup.py
src/bioservices/__init__.py
src/bioservices/_compat.py
src/bioservices/arrayexpress.py
src/bioservices/bigg.py
src/bioservices/biocontainers.py
src/bioservices/biodbnet.py
src/bioservices/biogrid.py
src/bioservices/biomart.py
src/bioservices/biomodels.py
src/bioservices/chebi.py
src/bioservices/chembl.py
src/bioservices/cog.py
src/bioservices/dbfetch.py
src/bioservices/ena.py
src/bioservices/ensembl.py
src/bioservices/eutils.py
src/bioservices/eva.py
src/bioservices/hgnc.py
src/bioservices/intact.py
src/bioservices/kegg.py
src/bioservices/main.py
src/bioservices/muscle.py
src/bioservices/mygeneinfo.py
src/bioservices/ncbiblast.py
src/bioservices/omicsdi.py
src/bioservices/omnipath.py
src/bioservices/panther.py
src/bioservices/pathwaycommons.py
src/bioservices/pdb.py
src/bioservices/pdbe.py
src/bioservices/pfam.py
src/bioservices/pride.py
src/bioservices/psicquic.py
src/bioservices/pubchem.py
src/bioservices/quickgo.py
src/bioservices/reactome.py
src/bioservices/rhea.py
src/bioservices/seqret.py
src/bioservices/services.py
src/bioservices/settings.py
src/bioservices/unichem.py
src/bioservices/uniprot.py
src/bioservices/util.py
src/bioservices/wikipathway.py
src/bioservices/xmltools.py
src/bioservices.egg-info/PKG-INFO
src/bioservices.egg-info/SOURCES.txt
src/bioservices.egg-info/dependency_links.txt
src/bioservices.egg-info/entry_points.txt
src/bioservices.egg-info/requires.txt
src/bioservices.egg-info/top_level.txt
src/bioservices/apps/__init__.py
src/bioservices/apps/download_fasta.py
src/bioservices/apps/download_gbk.py
src/bioservices/apps/download_gff3.py
src/bioservices/apps/fasta.py
src/bioservices/apps/peptides.py
src/bioservices/mapping/__init__.py
src/bioservices/mapping/mappers.py
src/bioservices/mapping/mapping.py