Metadata-Version: 2.1
Name: bioservices
Version: 1.11.2
Summary: Access to Biological Web Services from Python
Home-page: http://github.com/cokelaer/bioservices
Author: Thomas Cokelaer
Author-email: thomas.cokelaer@pasteur.fr
Maintainer: Thomas Cokelaer
Maintainer-email: thomas.cokelaer@pasteur.fr
License: GPLv3
Download-URL: http://pypi.python.org/pypi/bioservices
Keywords: BioServices,WebServices,Biology,BioDBNet,ChEBI,UniChem,Kegg,KEGG,BioModels,EUtils,UniProt,PICR,ArrayExpress,MUSCLE,QuickGO,PDB,PSICQUIC,Blast,BioMART,PantherDB,BioGRID,MIRIAM,BioMart,GeneProf,ChEMBL,ChemSpider,HGNC,PathwayCommons,Rhea,Ensembl
Platform: Linux
Platform: Unix
Platform: MacOsX
Platform: Windows
Classifier: Development Status :: 5 - Production/Stable
Classifier: Intended Audience :: Developers
Classifier: Intended Audience :: Science/Research
Classifier: License :: OSI Approved :: GNU General Public License v3 (GPLv3)
Classifier: Operating System :: OS Independent
Classifier: Programming Language :: Python :: 3.7
Classifier: Programming Language :: Python :: 3.8
Classifier: Programming Language :: Python :: 3.9
Classifier: Topic :: Software Development :: Libraries :: Python Modules
Classifier: Topic :: Scientific/Engineering :: Bio-Informatics
Classifier: Topic :: Scientific/Engineering :: Information Analysis
Classifier: Topic :: Scientific/Engineering :: Mathematics
Classifier: Topic :: Scientific/Engineering :: Physics
Provides-Extra: testing
